trepudox_py_utils/__init__.py
trepudox_py_utils/logging.py
trepudox_py_utils-0.0.2.dist-info/LICENSE.txt
trepudox_py_utils-0.0.2.dist-info/METADATA
trepudox_py_utils-0.0.2.dist-info/WHEEL
trepudox_py_utils-0.0.2.dist-info/top_level.txt
trepudox_py_utils-0.0.2.dist-info/RECORD
