Metadata-Version: 2.1
Name: trepudox_py_utils
Version: 0.0.2
Summary: This lib is intended to have some utilities that I use in my projects
Home-page: https://github.com/trepudox/trepudox_py_utils
Author: trepudox
Author-email: teoaa2@gmail.com
Classifier: Programming Language :: Python :: 3
Classifier: License :: OSI Approved :: GNU General Public License v3 (GPLv3)
Classifier: Operating System :: OS Independent
Classifier: Development Status :: 3 - Alpha
Classifier: Topic :: Software Development :: Libraries :: Python Modules
Requires-Python: >=3.7
License-File: LICENSE.txt
